fast_license/__init__.py
fast_license/__main__.py
fast_license/api_manager.cpython-311-darwin.so
fast_license/api_manager.pyi
fast_license/license.cpython-311-darwin.so
fast_license/license.pyi
fast_license/middleware.cpython-311-darwin.so
fast_license/middleware.pyi
fast_license-0.1.1.dist-info/METADATA
fast_license-0.1.1.dist-info/WHEEL
fast_license-0.1.1.dist-info/top_level.txt
fast_license-0.1.1.dist-info/RECORD
