Metadata-Version: 2.1
Name: fast-license
Version: 0.1.1
Summary: Easy way to handle License
Author: Bigollo
Requires-Dist: cryptography
